{
  "quotations": {
    "1234_dummy_quotation.pdf": {
      "quotation_number": null,
      "quotation_date": "08-Aug-2025",
      "valid_until": null,
      "supplier_name": "ABC Pvt. Ltd.",
      "supplier_address": "123 Industrial Area, Hyderabad, India",
      "supplier_contact": null,
      "supplier_phone": null,
      "supplier_email": null,
      "client_name": "XYZ Industries",
      "client_address": "Plot 456, Tech Park, Bangalore, India",
      "client_contact": null,
      "delivery_location": null,
      "delivery_terms": null,
      "payment_terms": null,
      "total_amount": 36580.0,
      "currency": "INR",
      "tax_amount": 5580.0,
      "discount_amount": null,
      "line_items": [
        {
          "item_number": "PN001",
          "description": "Hydraulic Pump",
          "quantity": 10,
          "unit_price": 2500.0,
          "total_price": 25000.0,
          "currency": "INR",
          "specifications": null
        },
        {
          "item_number": "PN002",
          "description": "Pressure Gauge",
          "quantity": 5,
          "unit_price": 1200.0,
          "total_price": 6000.0,
          "currency": "INR",
          "specifications": null
        }
      ],
      "terms_conditions": [
        "Terms & Conditions apply."
      ],
      "confidence_score": 0.8,
      "missing_fields": [
        "quotation_number",
        "valid_until",
        "supplier_contact",
        "supplier_phone",
        "supplier_email",
        "delivery_location",
        "delivery_terms",
        "payment_terms"
      ],
      "requires_review": true,
      "source_file": "dummy_quotation.pdf",
      "success": true,
      "message": "Quotation processed from dummy_quotation.pdf",
      "email_subject": "Indent 1234",
      "sender": "Romil Pandya <romilpandya.ai@gmail.com>",
      "email_date": "2025-08-08T14:08:46+05:30",
      "indent_id": "1234",
      "filename": "dummy_quotation.pdf",
      "processed_date": "2025-08-11T17:27:03.946930",
      "quotation_key": "1234_dummy_quotation.pdf"
    },
    "456_dummy_quotation.pdf": {
      "quotation_number": null,
      "quotation_date": "08-Aug-2025",
      "valid_until": null,
      "supplier_name": "ABC Pvt. Ltd.",
      "supplier_address": "123 Industrial Area, Hyderabad, India",
      "supplier_contact": null,
      "supplier_phone": null,
      "supplier_email": null,
      "client_name": "XYZ Industries",
      "client_address": "Plot 456, Tech Park, Bangalore, India",
      "client_contact": null,
      "delivery_location": null,
      "delivery_terms": null,
      "payment_terms": null,
      "total_amount": 36580.0,
      "currency": "INR",
      "tax_amount": 5580.0,
      "discount_amount": null,
      "line_items": [
        {
          "item_number": "PN001",
          "description": "Hydraulic Pump",
          "quantity": 10,
          "unit_price": 2500.0,
          "total_price": 25000.0,
          "currency": "INR",
          "specifications": null
        },
        {
          "item_number": "PN002",
          "description": "Pressure Gauge",
          "quantity": 5,
          "unit_price": 1200.0,
          "total_price": 6000.0,
          "currency": "INR",
          "specifications": null
        }
      ],
      "terms_conditions": [
        "Terms & Conditions apply."
      ],
      "confidence_score": 0.8,
      "missing_fields": [
        "quotation_number",
        "valid_until",
        "supplier_contact",
        "supplier_phone",
        "supplier_email",
        "delivery_location",
        "delivery_terms",
        "payment_terms"
      ],
      "requires_review": true,
      "source_file": "dummy_quotation.pdf",
      "success": true,
      "message": "Quotation processed from dummy_quotation.pdf",
      "email_subject": "Indent 456",
      "sender": "Romil Pandya <romilpandya.ai@gmail.com>",
      "email_date": "2025-08-08T14:05:53+05:30",
      "indent_id": "456",
      "filename": "dummy_quotation.pdf",
      "processed_date": "2025-08-08T18:56:08.527260",
      "quotation_key": "456_dummy_quotation.pdf"
    },
    "1234_dummy_quote.pdf": {
      "quotation_number": "",
      "quotation_date": "",
      "valid_until": "",
      "supplier_name": "Skyroot Aerospace Pvt. Ltd.",
      "supplier_address": "Hyderabad, India",
      "supplier_contact": "",
      "supplier_phone": "",
      "supplier_email": "",
      "client_name": "ABC Enterprises",
      "client_address": "Bangalore, India",
      "client_contact": "",
      "delivery_location": "",
      "delivery_terms": "",
      "payment_terms": "",
      "total_amount": 36580.0,
      "currency": "INR",
      "tax_amount": 5580.0,
      "discount_amount": 0.0,
      "line_items": [
        {
          "item_number": "PN001",
          "description": "Hydraulic Pump",
          "quantity": 10,
          "unit_price": 2500.0,
          "total_price": 25000.0,
          "currency": "INR",
          "specifications": ""
        },
        {
          "item_number": "PN002",
          "description": "Pressure Gauge",
          "quantity": 5,
          "unit_price": 1200.0,
          "total_price": 6000.0,
          "currency": "INR",
          "specifications": ""
        }
      ],
      "terms_conditions": [],
      "confidence_score": 0.8,
      "missing_fields": [
        "quotation_number",
        "quotation_date",
        "valid_until",
        "supplier_contact",
        "supplier_phone",
        "supplier_email",
        "client_contact",
        "delivery_location",
        "delivery_terms",
        "payment_terms"
      ],
      "requires_review": true,
      "source_file": "dummy_quote.pdf",
      "success": true,
      "message": "Quotation processed from dummy_quote.pdf",
      "email_subject": "Indent id 1234",
      "sender": "\"Romil M. Pandya\" <rmp71296@gmail.com>",
      "email_date": "2025-08-08T13:01:40+05:30",
      "indent_id": "1234",
      "filename": "dummy_quote.pdf",
      "processed_date": "2025-08-08T21:39:53.806344",
      "quotation_key": "1234_dummy_quote.pdf"
    },
    "1234_Vertex_Systems_quotation.pdf": {
      "quotation_number": "",
      "quotation_date": "08-Aug-2025",
      "valid_until": "",
      "supplier_name": "Vertex Systems",
      "supplier_address": "123 Industrial Hub, Hyderabad, India",
      "supplier_contact": "",
      "supplier_phone": "",
      "supplier_email": "",
      "client_name": "XYZ Industries",
      "client_address": "Plot 456, Tech Park, Bangalore, India",
      "client_contact": "",
      "delivery_location": "",
      "delivery_terms": "",
      "payment_terms": "",
      "total_amount": 38767.07,
      "currency": "INR",
      "tax_amount": 5913.62,
      "discount_amount": 0.0,
      "line_items": [
        {
          "item_number": "PN001",
          "description": "Hydraulic Pump",
          "quantity": 10,
          "unit_price": 2645.96,
          "total_price": 26459.6,
          "currency": "INR",
          "specifications": ""
        },
        {
          "item_number": "PN002",
          "description": "Pressure Gauge",
          "quantity": 5,
          "unit_price": 1278.77,
          "total_price": 6393.85,
          "currency": "INR",
          "specifications": ""
        }
      ],
      "terms_conditions": [
        "Terms & Conditions apply."
      ],
      "confidence_score": 0.9,
      "missing_fields": [
        "quotation_number",
        "valid_until",
        "supplier_contact",
        "supplier_phone",
        "supplier_email",
        "client_contact",
        "delivery_location",
        "delivery_terms",
        "payment_terms"
      ],
      "requires_review": true,
      "source_file": "Vertex_Systems_quotation.pdf",
      "success": true,
      "message": "Quotation processed from Vertex_Systems_quotation.pdf",
      "email_subject": "Indent 1234",
      "sender": "Romil Aditi <romiladiti.2107@gmail.com>",
      "email_date": "2025-08-11T11:33:21+05:30",
      "indent_id": "1234",
      "filename": "Vertex_Systems_quotation.pdf",
      "processed_date": "2025-08-11T11:37:22.759182",
      "quotation_key": "1234_Vertex_Systems_quotation.pdf"
    },
    "1234_Omega_Industries_Pvt._Ltd._quotation.pdf": {
      "quotation_number": null,
      "quotation_date": "08-Aug-2025",
      "valid_until": null,
      "supplier_name": "Omega Industries Pvt. Ltd.",
      "supplier_address": "123 Industrial Hub, Hyderabad, India",
      "supplier_contact": null,
      "supplier_phone": null,
      "supplier_email": null,
      "client_name": "XYZ Industries",
      "client_address": "Plot 456, Tech Park, Bangalore, India",
      "client_contact": null,
      "delivery_location": null,
      "delivery_terms": null,
      "payment_terms": null,
      "total_amount": 38608.18,
      "currency": "INR",
      "tax_amount": 5889.38,
      "discount_amount": null,
      "line_items": [
        {
          "item_number": "PN001",
          "description": "Hydraulic Pump",
          "quantity": 10,
          "unit_price": 2710.39,
          "total_price": 27103.9,
          "currency": "INR",
          "specifications": null
        },
        {
          "item_number": "PN002",
          "description": "Pressure Gauge",
          "quantity": 5,
          "unit_price": 1122.98,
          "total_price": 5614.9,
          "currency": "INR",
          "specifications": null
        }
      ],
      "terms_conditions": [
        "Terms & Conditions apply."
      ],
      "confidence_score": 0.8,
      "missing_fields": [
        "quotation_number",
        "valid_until",
        "supplier_contact",
        "supplier_phone",
        "supplier_email",
        "client_contact",
        "delivery_location",
        "delivery_terms",
        "payment_terms"
      ],
      "requires_review": true,
      "source_file": "Omega_Industries_Pvt._Ltd._quotation.pdf",
      "success": true,
      "message": "Quotation processed from Omega_Industries_Pvt._Ltd._quotation.pdf",
      "email_subject": "Indent 1234",
      "sender": "The DREAMR <dreamsncolors1@gmail.com>",
      "email_date": "2025-08-11T11:33:53+05:30",
      "indent_id": "1234",
      "filename": "Omega_Industries_Pvt._Ltd._quotation.pdf",
      "processed_date": "2025-08-11T11:37:32.022721",
      "quotation_key": "1234_Omega_Industries_Pvt._Ltd._quotation.pdf"
    },
    "1234_Delta_Engineering_Ltd._quotation.pdf": {
      "quotation_number": null,
      "quotation_date": "08-Aug-2025",
      "valid_until": null,
      "supplier_name": "Delta Engineering Ltd.",
      "supplier_address": "123 Industrial Hub, Hyderabad, India",
      "supplier_contact": null,
      "supplier_phone": null,
      "supplier_email": null,
      "client_name": "XYZ Industries",
      "client_address": "Plot 456, Tech Park, Bangalore, India",
      "client_contact": null,
      "delivery_location": null,
      "delivery_terms": null,
      "payment_terms": null,
      "total_amount": 34098.52,
      "currency": "INR",
      "tax_amount": 5201.47,
      "discount_amount": null,
      "line_items": [
        {
          "item_number": "PN001",
          "description": "Hydraulic Pump",
          "quantity": 10,
          "unit_price": 2307.82,
          "total_price": 23078.2,
          "currency": "INR",
          "specifications": null
        },
        {
          "item_number": "PN002",
          "description": "Pressure Gauge",
          "quantity": 5,
          "unit_price": 1163.77,
          "total_price": 5818.85,
          "currency": "INR",
          "specifications": null
        }
      ],
      "terms_conditions": [
        "Terms & Conditions apply."
      ],
      "confidence_score": 0.9,
      "missing_fields": [
        "quotation_number",
        "valid_until",
        "supplier_contact",
        "supplier_phone",
        "supplier_email",
        "client_contact",
        "delivery_location",
        "delivery_terms",
        "payment_terms"
      ],
      "requires_review": true,
      "source_file": "Delta_Engineering_Ltd._quotation.pdf",
      "success": true,
      "message": "Quotation processed from Delta_Engineering_Ltd._quotation.pdf",
      "email_subject": "Indent 1234",
      "sender": "Romil Pandya <romilpandya01@gmail.com>",
      "email_date": "2025-08-11T11:34:18+05:30",
      "indent_id": "1234",
      "filename": "Delta_Engineering_Ltd._quotation.pdf",
      "processed_date": "2025-08-11T11:37:48.460876",
      "quotation_key": "1234_Delta_Engineering_Ltd._quotation.pdf"
    },
    "1234_Prime_Tech_Solutions_quotation.pdf": {
      "quotation_number": null,
      "quotation_date": "08-Aug-2025",
      "valid_until": null,
      "supplier_name": "Prime Tech Solutions",
      "supplier_address": "123 Industrial Hub, Hyderabad, India",
      "supplier_contact": null,
      "supplier_phone": null,
      "supplier_email": null,
      "client_name": "XYZ Industries",
      "client_address": "Plot 456, Tech Park, Bangalore, India",
      "client_contact": null,
      "delivery_location": null,
      "delivery_terms": null,
      "payment_terms": null,
      "total_amount": 38187.63,
      "currency": "INR",
      "tax_amount": 5825.23,
      "discount_amount": null,
      "line_items": [
        {
          "item_number": "PN001",
          "description": "Hydraulic Pump",
          "quantity": 10,
          "unit_price": 2641.84,
          "total_price": 26418.4,
          "currency": "INR",
          "specifications": null
        },
        {
          "item_number": "PN002",
          "description": "Pressure Gauge",
          "quantity": 5,
          "unit_price": 1188.8,
          "total_price": 5944.0,
          "currency": "INR",
          "specifications": null
        }
      ],
      "terms_conditions": [
        "Terms & Conditions apply."
      ],
      "confidence_score": 0.8,
      "missing_fields": [
        "quotation_number",
        "valid_until",
        "supplier_contact",
        "supplier_phone",
        "supplier_email",
        "delivery_location",
        "delivery_terms",
        "payment_terms"
      ],
      "requires_review": true,
      "source_file": "Prime_Tech_Solutions_quotation.pdf",
      "success": true,
      "message": "Quotation processed from Prime_Tech_Solutions_quotation.pdf",
      "email_subject": "Indent 1234",
      "sender": "\"Romil M. Pandya\" <rmp71296@gmail.com>",
      "email_date": "2025-08-11T11:32:45+05:30",
      "indent_id": "1234",
      "filename": "Prime_Tech_Solutions_quotation.pdf",
      "processed_date": "2025-08-11T11:38:08.851056",
      "quotation_key": "1234_Prime_Tech_Solutions_quotation.pdf"
    },
    "1234_Nova_Equipments_quotation.pdf": {
      "quotation_number": null,
      "quotation_date": "08-Aug-2025",
      "valid_until": null,
      "supplier_name": "Nova Equipments",
      "supplier_address": "123 Industrial Hub, Hyderabad, India",
      "supplier_contact": null,
      "supplier_phone": null,
      "supplier_email": null,
      "client_name": "XYZ Industries",
      "client_address": "Plot 456, Tech Park, Bangalore, India",
      "client_contact": null,
      "delivery_location": null,
      "delivery_terms": null,
      "payment_terms": null,
      "total_amount": 36452.44,
      "currency": "INR",
      "tax_amount": 5560.54,
      "discount_amount": null,
      "line_items": [
        {
          "item_number": "PN001",
          "description": "Hydraulic Pump",
          "quantity": 10,
          "unit_price": 2508.76,
          "total_price": 25087.6,
          "currency": "INR",
          "specifications": null
        },
        {
          "item_number": "PN002",
          "description": "Pressure Gauge",
          "quantity": 5,
          "unit_price": 1160.86,
          "total_price": 5804.3,
          "currency": "INR",
          "specifications": null
        }
      ],
      "terms_conditions": [
        "Terms & Conditions apply."
      ],
      "confidence_score": 0.8,
      "missing_fields": [
        "quotation_number",
        "valid_until",
        "supplier_contact",
        "supplier_phone",
        "supplier_email",
        "delivery_location",
        "delivery_terms",
        "payment_terms"
      ],
      "requires_review": true,
      "source_file": "Nova_Equipments_quotation.pdf",
      "success": true,
      "message": "Quotation processed from Nova_Equipments_quotation.pdf",
      "email_subject": "Indent id 1234",
      "sender": "Romil Pandya <romilpandya.ai@gmail.com>",
      "email_date": "2025-08-11T11:32:11+05:30",
      "indent_id": "1234",
      "filename": "Nova_Equipments_quotation.pdf",
      "processed_date": "2025-08-11T11:38:25.329740",
      "quotation_key": "1234_Nova_Equipments_quotation.pdf"
    },
    "789_Rapid_Engineering_Works_quotation.pdf": {
      "quotation_number": null,
      "quotation_date": "08-Aug-2025",
      "valid_until": null,
      "supplier_name": "Rapid Engineering Works",
      "supplier_address": "456 Industrial Estate, Mumbai, India",
      "supplier_contact": null,
      "supplier_phone": null,
      "supplier_email": null,
      "client_name": "XYZ Industries",
      "client_address": "Plot 456, Tech Park, Bangalore, India",
      "client_contact": null,
      "delivery_location": null,
      "delivery_terms": null,
      "payment_terms": null,
      "total_amount": 93354.33,
      "currency": "I",
      "tax_amount": 14240.49,
      "discount_amount": null,
      "line_items": [
        {
          "item_number": "PN101",
          "description": "Industrial Motor",
          "quantity": 3,
          "unit_price": 15091.33,
          "total_price": 45273.99,
          "currency": "I",
          "specifications": null
        },
        {
          "item_number": "PN102",
          "description": "Control Valve",
          "quantity": 7,
          "unit_price": 3235.83,
          "total_price": 22650.81,
          "currency": "I",
          "specifications": null
        },
        {
          "item_number": "PN103",
          "description": "Safety Switch",
          "quantity": 12,
          "unit_price": 932.42,
          "total_price": 11189.04,
          "currency": "I",
          "specifications": null
        }
      ],
      "terms_conditions": [
        "Terms & Conditions apply."
      ],
      "confidence_score": 0.9,
      "missing_fields": [
        "quotation_number",
        "valid_until",
        "supplier_contact",
        "supplier_phone",
        "supplier_email",
        "delivery_location",
        "delivery_terms",
        "payment_terms"
      ],
      "requires_review": true,
      "source_file": "Rapid_Engineering_Works_quotation.pdf",
      "success": true,
      "message": "Quotation processed from Rapid_Engineering_Works_quotation.pdf",
      "email_subject": "Indent 789",
      "sender": "Romil Pandya <romilpandya.ai@gmail.com>",
      "email_date": "2025-08-11T17:09:03+05:30",
      "indent_id": "789",
      "filename": "Rapid_Engineering_Works_quotation.pdf",
      "processed_date": "2025-08-11T17:25:18.682927",
      "quotation_key": "789_Rapid_Engineering_Works_quotation.pdf"
    }
  },
  "metadata": {
    "created_date": "2025-08-08T17:31:40.033798",
    "version": "1.0",
    "total_quotations": 9,
    "last_updated": "2025-08-11T17:27:03.946943"
  }
}